DepthFlow/__init__.py
depthflow-2024.1.15.dist-info/METADATA
depthflow-2024.1.15.dist-info/WHEEL
depthflow-2024.1.15.dist-info/RECORD
