Metadata-Version: 2.1
Name: depthflow
Version: 2024.1.15
Summary: Reserving pypi namespace
License: AGPLv3-only
Author: Tremeschin
Author-email: 29046864+Tremeschin@users.noreply.github.com
Requires-Python: >=3.11,<4.0
Classifier: License :: Other/Proprietary License
Classifier: Programming Language :: Python :: 3
Classifier: Programming Language :: Python :: 3.11
Classifier: Programming Language :: Python :: 3.12
